MANIFEST.in
setup.py
canalysis/__init__.py
canalysis/analysis.py
canalysis/emoji.py
canalysis/lda_gibbs.py
canalysis/lda_template.py
canalysis/ml.py
canalysis/ml_utilities.py
canalysis/nmfsc.py
canalysis/nmfsc_test.py
canalysis/sentiment.py
canalysis/stats.py
cchen224_ec2.egg-info/PKG-INFO
cchen224_ec2.egg-info/SOURCES.txt
cchen224_ec2.egg-info/dependency_links.txt
cchen224_ec2.egg-info/requires.txt
cchen224_ec2.egg-info/top_level.txt
cchen224_ec2.egg-info/zip-safe
pyAPIs/__init__.py
pyAPIs/foursquare/__init__.py
pyAPIs/foursquare/access_tokens.py
pyAPIs/foursquare/main.py
pyAPIs/foursquare/parser_location.py
pyAPIs/instagram/GetPhotoByUsername.py
pyAPIs/instagram/__init__.py
pyAPIs/instagram/access_tokens.py
pyAPIs/instagram/main.py
pyAPIs/instagram/parser_media.py
pyAPIs/instagram/parser_user_info.py
pyAPIs/twitter/__init__.py
pyAPIs/twitter/twitter_accounts.py
pyAPIs/twitter/twitter_followers.py
pyAPIs/twitter/twitter_followers_NFL.py
pyAPIs/twitter/twitter_following.py
pyAPIs/twitter/twitter_timeline.py
pyAPIs/twitter/twitter_user.py
pycrawlers/__init__.py
pycrawlers/requests_util.py
pycrawlers/twitter/__init__.py
pycrawlers/twitter/crawl_tweets.py
pycrawlers/twitter/main.py
pycrawlers/twitter/webparser_error.py
pycrawlers/twitter/webparser_threads.py
pycrawlers/twitter/webparser_tweet.py
pycrawlers/twitter/webparser_user_info.py
pycrawlers/twitter/webparser_user_timeline.py
pycrawlers/twitter/webparser_utility.py
pycrawlers/zillow/__init__.py
pycrawlers/zillow/main.py
pycrawlers/zillow/template.py
pycrawlers/zillow/webparser.py