Metadata-Version: 1.0
Name: cchen224-ec2
Version: 0.0.147
Summary: cc personal use for AWS
Home-page: UNKNOWN
Author: cchen224
Author-email: phantomkidding@gmail.com
License: MIT License
Keywords: ec2,cchen224
Platform: any
